oshit/__init__.py
oshit/__main__.py
oshit/app/__init__.py
oshit/app/commands.py
oshit/app/oshit.py
oshit/app/data/__init__.py
oshit/app/data/config.py
oshit/app/data/locations.py
oshit/app/screens/__init__.py
oshit/app/screens/comments.py
oshit/app/screens/config.py
oshit/app/screens/help.py
oshit/app/screens/links.py
oshit/app/screens/main.py
oshit/app/screens/search.py
oshit/app/screens/user.py
oshit/app/widgets/__init__.py
oshit/app/widgets/article_text.py
oshit/app/widgets/comment_card.py
oshit/app/widgets/hacker_news.py
oshit/app/widgets/items.py
oshit/hn/__init__.py
oshit/hn/client.py
oshit/hn/text.py
oshit/hn/user.py
oshit/hn/item/__init__.py
oshit/hn/item/article.py
oshit/hn/item/base.py
oshit/hn/item/comment.py
oshit/hn/item/link.py
oshit/hn/item/loader.py
oshit/hn/item/poll.py
oshit/hn/item/unknown.py
oshit-1.0.0.dist-info/METADATA
oshit-1.0.0.dist-info/WHEEL
oshit-1.0.0.dist-info/entry_points.txt
oshit-1.0.0.dist-info/licenses/LICENSE
oshit-1.0.0.dist-info/RECORD
