Metadata-Version: 2.3
Name: oshit
Version: 1.0.0
Summary: A terminal-based HackerNews reader
Project-URL: Homepage, https://github.com/davep/oshit
Project-URL: Repository, https://github.com/davep/oshit
Project-URL: Documentation, https://github.com/davep/oshit
Project-URL: Source, https://github.com/davep/oshit
Project-URL: Issues, https://github.com/davep/oshit/issues
Project-URL: Discussions, https://github.com/davep/oshit/discussions
Author-email: Dave Pearson <davep@davep.org>
License: GNU General Public License v3 or later (GPLv3+)
Keywords: chui,hacker-news,hackernews,news,orange-site,reader,terminal,tui
Classifier: Development Status :: 5 - Production/Stable
Classifier: Environment :: Console
Classifier: Intended Audience :: End Users/Desktop
Classifier: License :: OSI Approved :: GNU General Public License v3 or later (GPLv3+)
Classifier: Natural Language :: English
Classifier: Operating System :: OS Independent
Classifier: Programming Language :: Python :: 3.10
Classifier: Programming Language :: Python :: 3.11
Classifier: Programming Language :: Python :: 3.12
Classifier: Programming Language :: Python :: 3.13
Classifier: Topic :: Internet
Classifier: Topic :: Terminals
Classifier: Typing :: Typed
Requires-Python: >=3.10
Requires-Dist: httpx
Requires-Dist: humanize>=4.8.0
Requires-Dist: textual>=3.5.0
Requires-Dist: xdg-base-dirs>=6.0.0
